insteon/__init__.py
insteon/util.py
insteon/dev/__init__.py
insteon/dev/dbmanager.py
insteon/dev/device.py
insteon/dev/light.py
insteon/dev/linkdb.py
insteon/dev/linker.py
insteon/dev/modem.py
insteon/dev/network.py
insteon/dev/querier.py
insteon/io/__init__.py
insteon/io/address.py
insteon/io/hub.py
insteon/io/hubsrv.py
insteon/io/message.py
insteon/io/message_def.py
insteon/io/msg_definitions.xml
insteon/io/port.py
insteon/io/serial.py
insteon/io/xmlmsgreader.py
insteon-0.0.2.dist-info/LICENSE
insteon-0.0.2.dist-info/METADATA
insteon-0.0.2.dist-info/WHEEL
insteon-0.0.2.dist-info/top_level.txt
insteon-0.0.2.dist-info/RECORD
